{
  "type": "Feature",
  "properties": {
    "addr:full":"4528 Ellicott St NW Washington MD 20016",
    "addr:housenumber":"4528",
    "addr:postcode":"20016",
    "addr:street":"Ellicott St Nw",
    "iso:country":"US",
    "sg:address":"4528 Ellicott St NW",
    "sg:city":"Washington",
    "sg:classifiers":[
        {
            "category":"Social Services",
            "type":"Services"
        }
    ],
    "sg:phone":"+1 301 652 9050",
    "sg:postcode":"20016",
    "sg:province":"MD",
    "sg:tags":[
        "worker"
    ],
    "wof:name":"Beatrice Liebenberg",
    "wof:placetype":"venue"
},
  "geometry": {"coordinates":[-77.09014500000001,38.953242],"type":"Point"}
}