{
  "type": "Feature",
  "properties": {
    "iso:country":"US",
    "sg:address":"8070 Georgia Ave",
    "sg:city":"Silver Spring",
    "sg:classifiers":[
        {
            "category":"Communications",
            "type":"Services"
        }
    ],
    "sg:phone":"+1 301 585 4481",
    "sg:postcode":"20910",
    "sg:province":"MD",
    "wof:name":"Flash Talk Communications",
    "wof:placetype":"venue"
},
  "geometry": {"coordinates":[-77.026737,38.987444],"type":"Point"}
}