{
  "type": "Feature",
  "properties": {
    "iso:country":"US",
    "sg:address":"824 Upshur St NW",
    "sg:city":"Washington",
    "sg:classifiers":[
        {
            "category":"Health Services",
            "subcategory":"Clinic",
            "type":"Services"
        }
    ],
    "sg:phone":"+1 202 545 0810",
    "sg:postcode":"20011",
    "sg:province":"MD",
    "sg:tags":[
        "home"
    ],
    "wof:name":"Superior Business Svc",
    "wof:placetype":"venue"
},
  "geometry": {"coordinates":[-77.025497,38.941798],"type":"Point"}
}