{
  "type": "Feature",
  "properties": {
    "iso:country":"US",
    "sg:address":"603 Gallatin St NW",
    "sg:city":"Washington",
    "sg:classifiers":[
        {
            "category":"Building & Trades",
            "subcategory":"Construction",
            "type":"Services"
        }
    ],
    "sg:phone":"+1 202 258 0211",
    "sg:postcode":"20011",
    "sg:province":"MD",
    "sg:tags":[
        "home",
        "improvement"
    ],
    "wof:name":"Margni Inc",
    "wof:placetype":"venue"
},
  "geometry": {"coordinates":[-77.02093,38.952126],"type":"Point"}
}