{
  "type": "Feature",
  "properties": {
    "addr:full":"1351 Ingraham St NW Washington MD 20011",
    "addr:housenumber":"1351",
    "addr:postcode":"20011",
    "addr:street":"Ingraham St Nw",
    "iso:country":"US",
    "sg:address":"1351 Ingraham St NW",
    "sg:city":"Washington",
    "sg:classifiers":[
        {
            "category":"Retail",
            "subcategory":"Laundry & Dry Cleaning",
            "type":"Services"
        }
    ],
    "sg:phone":"+1 202 498 1355",
    "sg:postcode":"20011",
    "sg:province":"MD",
    "sg:tags":[
        "cleaners",
        "rug",
        "carpet"
    ],
    "wof:name":"Heaven's Best Carpet Cleaning",
    "wof:placetype":"venue"
},
  "geometry": {"coordinates":[-77.031947,38.954162],"type":"Point"}
}