{
  "type": "Feature",
  "properties": {
    "iso:country":"US",
    "sg:address":"4958 Butterworth Pl NW",
    "sg:city":"Washington",
    "sg:classifiers":[
        {
            "category":"Organizations",
            "subcategory":"Non-profit Organization",
            "type":"Services"
        }
    ],
    "sg:phone":"+1 202 244 2443",
    "sg:postcode":"20016",
    "sg:province":"MD",
    "wof:name":"NATSPP",
    "wof:placetype":"venue"
},
  "geometry": {"coordinates":[-77.09871,38.948727],"type":"Point"}
}