{
  "type": "Feature",
  "properties": {
    "addr:full":"4404 Springdale St NW Washington MD 20016",
    "addr:housenumber":"4404",
    "addr:postcode":"20016",
    "addr:street":"Springdale St Nw",
    "iso:country":"US",
    "sg:address":"4404 Springdale St NW",
    "sg:city":"Washington",
    "sg:classifiers":[
        {
            "category":"Organizations",
            "subcategory":"Religious Organization",
            "type":"Services"
        }
    ],
    "sg:phone":"+1 202 966 4404",
    "sg:postcode":"20016",
    "sg:province":"MD",
    "sg:tags":[
        "clergy"
    ],
    "wof:name":"James A Langley",
    "wof:placetype":"venue"
},
  "geometry": {"coordinates":[-77.087946,38.942069],"type":"Point"}
}