{
  "type": "Feature",
  "properties": {
    "addr:full":"7112 Willow Ave Takoma Park MD 20912",
    "addr:housenumber":"7112",
    "addr:postcode":"20912",
    "addr:street":"Willow Ave",
    "iso:country":"US",
    "sg:address":"7112 Willow Ave",
    "sg:city":"Takoma Park",
    "sg:classifiers":[
        {
            "category":"Professional",
            "subcategory":"Detective & Security Services",
            "type":"Services"
        }
    ],
    "sg:phone":"+1 301 891 1210",
    "sg:postcode":"20912",
    "sg:province":"MD",
    "sg:tags":[
        "guard",
        "patrol"
    ],
    "wof:name":"Wackenhut Corp",
    "wof:placetype":"venue"
},
  "geometry": {"coordinates":[-77.01223,38.976105],"type":"Point"}
}