{
  "type": "Feature",
  "properties": {
    "addr:full":"7305 Georgia Ave NW Washington MD 20012",
    "addr:housenumber":"7305",
    "addr:postcode":"20012",
    "addr:street":"Georgia Ave Nw",
    "iso:country":"US",
    "sg:address":"7305 Georgia Ave NW",
    "sg:city":"Washington",
    "sg:classifiers":[
        {
            "category":"Personal",
            "subcategory":"Beauty Salon",
            "type":"Services"
        }
    ],
    "sg:phone":"+1 202 882 7415",
    "sg:postcode":"20012",
    "sg:province":"MD",
    "wof:name":"Bryan Joseph Salon",
    "wof:placetype":"venue"
},
  "geometry": {"coordinates":[-77.026383,38.979348],"type":"Point"}
}