{
  "type": "Feature",
  "properties": {
    "addr:full":"3613 Norton Pl NW Washington MD 20016",
    "addr:housenumber":"3613",
    "addr:postcode":"20016",
    "addr:street":"Norton Pl Nw",
    "iso:country":"US",
    "sg:address":"3613 Norton Pl NW",
    "sg:city":"Washington",
    "sg:classifiers":[
        {
            "category":"Professional",
            "subcategory":"Art Services",
            "type":"Services"
        }
    ],
    "sg:phone":"+1 202 244 0465",
    "sg:postcode":"20016",
    "sg:province":"MD",
    "sg:tags":[
        "graphic",
        "designer"
    ],
    "wof:name":"James Hellmuth",
    "wof:placetype":"venue"
},
  "geometry": {"coordinates":[-77.072669,38.935616],"type":"Point"}
}