{
  "type": "Feature",
  "properties": {
    "iso:country":"US",
    "sg:address":"7826 Eastern Ave NW",
    "sg:city":"Washington",
    "sg:classifiers":[
        {
            "category":"Building & Trades",
            "subcategory":"Cleaning & Sanitation",
            "type":"Services"
        }
    ],
    "sg:phone":"+1 202 722 2466",
    "sg:postcode":"20910",
    "sg:province":"MD",
    "sg:tags":[
        "janitor"
    ],
    "wof:name":"Unicorn Services",
    "wof:placetype":"venue"
},
  "geometry": {"coordinates":[-77.027427,38.985158],"type":"Point"}
}