{
  "type": "Feature",
  "properties": {
    "addr:full":"4115 Garrison St NW Washington MD 20016",
    "addr:housenumber":"4115",
    "addr:postcode":"20016",
    "addr:street":"Garrison St Nw",
    "iso:country":"US",
    "sg:address":"4115 Garrison St NW",
    "sg:city":"Washington",
    "sg:classifiers":[
        {
            "category":"Communications",
            "subcategory":"Film & Video Production",
            "type":"Services"
        }
    ],
    "sg:phone":"+1 202 686 7229",
    "sg:postcode":"20016",
    "sg:province":"MD",
    "sg:tags":[
        "motion",
        "picture",
        "studio",
        "producer"
    ],
    "wof:name":"Eyedeas",
    "wof:placetype":"venue"
},
  "geometry": {"coordinates":[-77.081834,38.956031],"type":"Point"}
}