{
  "type": "Feature",
  "properties": {
    "iso:country":"US",
    "sg:address":"1050 Barnaby Ter SE",
    "sg:city":"Washington",
    "sg:classifiers":[
        {
            "category":"Organizations",
            "subcategory":"Professional Association",
            "type":"Services"
        }
    ],
    "sg:phone":"+1 202 563 1779",
    "sg:postcode":"20032",
    "sg:province":"MD",
    "wof:name":"National Hand Dance Assn",
    "wof:placetype":"venue"
},
  "geometry": {"coordinates":[-76.988641,38.833507],"type":"Point"}
}