{
  "type": "Feature",
  "properties": {
    "iso:country":"US",
    "sg:address":"4646 40th St NW",
    "sg:city":"Washington",
    "sg:classifiers":[
        {
            "category":"Professional",
            "subcategory":"Business Services",
            "type":"Services"
        }
    ],
    "sg:phone":"+1 202 537 6700",
    "sg:postcode":"20016",
    "sg:province":"MD",
    "sg:tags":[
        "statistical"
    ],
    "wof:name":"Temple University-Institute",
    "wof:placetype":"venue"
},
  "geometry": {"coordinates":[-77.078814,38.950236],"type":"Point"}
}