{
  "type": "Feature",
  "properties": {
    "addr:full":"3232 Wisconsin Ave NW Washington MD 20016",
    "addr:housenumber":"3232",
    "addr:postcode":"20016",
    "addr:street":"Wisconsin Ave Nw",
    "iso:country":"US",
    "sg:address":"3232 Wisconsin Ave NW",
    "sg:city":"Washington",
    "sg:classifiers":[
        {
            "category":"Retail",
            "subcategory":"Laundry & Dry Cleaning",
            "type":"Services"
        }
    ],
    "sg:phone":"+1 202 363 3332",
    "sg:postcode":"20016",
    "sg:province":"MD",
    "sg:tags":[
        "cleaners"
    ],
    "wof:name":"Harvey's Custom Cleaners",
    "wof:placetype":"venue"
},
  "geometry": {"coordinates":[-77.072504,38.933288],"type":"Point"}
}