{
  "type": "Feature",
  "properties": {
    "addr:full":"3000 Branch Ave Temple Hills MD 20748",
    "addr:housenumber":"3000",
    "addr:postcode":"20748",
    "addr:street":"Branch Ave",
    "iso:country":"US",
    "sg:address":"3000 Branch Ave",
    "sg:city":"Temple Hills",
    "sg:classifiers":[
        {
            "category":"Organizations",
            "subcategory":"Religious Organization",
            "type":"Services"
        }
    ],
    "sg:phone":"+1 301 899 2727",
    "sg:postcode":"20748",
    "sg:province":"MD",
    "sg:tags":[
        "church"
    ],
    "wof:name":"Kendall Baptist Church",
    "wof:placetype":"venue"
},
  "geometry": {"coordinates":[-76.957931,38.854782],"type":"Point"}
}