{
  "type": "Feature",
  "properties": {
    "addr:full":"2942 2nd St SE Washington MD 20032",
    "addr:housenumber":"2942",
    "addr:postcode":"20032",
    "addr:street":"2Nd St Se",
    "iso:country":"US",
    "sg:address":"2942 2nd St SE",
    "sg:city":"Washington",
    "sg:classifiers":[
        {
            "category":"Real Estate",
            "subcategory":"Real Estate Operator",
            "type":"Services"
        }
    ],
    "sg:phone":"+1 202 562 5060",
    "sg:postcode":"20032",
    "sg:province":"MD",
    "sg:tags":[
        "apartment"
    ],
    "wof:name":"River Hill Apartments",
    "wof:placetype":"venue"
},
  "geometry": {"coordinates":[-77.003421,38.845541],"type":"Point"}
}