{
  "type": "Feature",
  "properties": {
    "iso:country":"US",
    "sg:address":"5415 Connecticut Ave NW",
    "sg:city":"Washington",
    "sg:classifiers":[
        {
            "category":"Travel",
            "subcategory":"Travel Agent",
            "type":"Entertainment"
        }
    ],
    "sg:phone":"+1 202 364 5091",
    "sg:postcode":"20015",
    "sg:province":"MD",
    "sg:tags":[
        "agency",
        "bureau"
    ],
    "wof:name":"Philoxenia International Trvl",
    "wof:placetype":"venue"
},
  "geometry": {"coordinates":[-77.073309,38.961017],"type":"Point"}
}