{
  "type": "Feature",
  "properties": {
    "iso:country":"US",
    "sg:address":"5704 Georgia Ave NW",
    "sg:city":"Washington",
    "sg:classifiers":[
        {
            "category":"Building & Trades",
            "subcategory":"Construction",
            "type":"Services"
        }
    ],
    "sg:phone":"+1 202 882 2006",
    "sg:postcode":"20011",
    "sg:province":"MD",
    "sg:tags":[
        "general",
        "contractor"
    ],
    "wof:name":"Prime Construction LLC",
    "wof:placetype":"venue"
},
  "geometry": {"coordinates":[-77.028113,38.96091],"type":"Point"}
}