{
  "type": "Feature",
  "properties": {
    "iso:country":"US",
    "sg:address":"6207 Blair Rd NW",
    "sg:city":"Washington",
    "sg:classifiers":[
        {
            "category":"Organizations",
            "subcategory":"Professional Association",
            "type":"Services"
        }
    ],
    "sg:phone":"+1 202 723 7101",
    "sg:postcode":"20012",
    "sg:province":"MD",
    "sg:tags":[
        "business",
        "trade"
    ],
    "wof:name":"Potomac Business Ctr",
    "wof:placetype":"venue"
},
  "geometry": {"coordinates":[-77.01269,38.96617],"type":"Point"}
}