{
  "type": "Feature",
  "properties": {
    "iso:country":"US",
    "sg:address":"4713 Kansas Ave NW",
    "sg:city":"Washington",
    "sg:classifiers":[
        {
            "category":"Retail",
            "subcategory":"Repair Shop",
            "type":"Services"
        }
    ],
    "sg:phone":"+1 202 722 1848",
    "sg:postcode":"20011",
    "sg:province":"MD",
    "sg:tags":[
        "lock",
        "locksmith"
    ],
    "sg:website":"www.actioncraft.net",
    "wof:name":"Action Craft",
    "wof:placetype":"venue"
},
  "geometry": {"coordinates":[-77.021047,38.94831],"type":"Point"}
}