{
  "type": "Feature",
  "properties": {
    "iso:country":"US",
    "sg:address":"24 Kennedy St NW",
    "sg:city":"Washington",
    "sg:classifiers":[
        {
            "category":"Organizations",
            "subcategory":"Professional Association",
            "type":"Services"
        }
    ],
    "sg:phone":"+1 202 829 8225",
    "sg:postcode":"20011",
    "sg:province":"MD",
    "sg:tags":[
        "business",
        "trade"
    ],
    "wof:name":"Christian Business Network",
    "wof:placetype":"venue"
},
  "geometry": {"coordinates":[-77.011509,38.956512],"type":"Point"}
}