{
  "type": "Feature",
  "properties": {
    "iso:country":"US",
    "sg:address":"6003 Central Ave",
    "sg:city":"Capitol Heights",
    "sg:classifiers":[
        {
            "category":"Shopping",
            "subcategory":"Used Merchandise",
            "type":"Retail Goods"
        }
    ],
    "sg:phone":"+1 301 420 6730",
    "sg:postcode":"20743",
    "sg:province":"MD",
    "sg:tags":[
        "shop",
        "thrift"
    ],
    "wof:name":"American Rescue Workers",
    "wof:placetype":"venue"
},
  "geometry": {"coordinates":[-76.914473,38.884782],"type":"Point"}
}