{
  "type": "Feature",
  "properties": {
    "iso:country":"US",
    "sg:address":"6076 Central Ave",
    "sg:city":"Capitol Heights",
    "sg:classifiers":[
        {
            "category":"Organizations",
            "subcategory":"Religious Organization",
            "type":"Services"
        }
    ],
    "sg:phone":"+1 301 808 5348",
    "sg:postcode":"20743",
    "sg:province":"MD",
    "sg:tags":[
        "church"
    ],
    "wof:name":"Iconium Baptist Church",
    "wof:placetype":"venue"
},
  "geometry": {"coordinates":[-76.910702,38.885093],"type":"Point"}
}