{
  "type": "Feature",
  "properties": {
    "addr:full":"3201 New Mexico Ave NW Washington MD 20016",
    "addr:housenumber":"3201",
    "addr:postcode":"20016",
    "addr:street":"New Mexico Ave Nw",
    "iso:country":"US",
    "sg:address":"3201 New Mexico Ave NW",
    "sg:city":"Washington",
    "sg:classifiers":[
        {
            "category":"Manufacturing",
            "subcategory":"Printing",
            "type":"Manufacturing & Wholesale Goods"
        }
    ],
    "sg:phone":"+1 202 895 1346",
    "sg:postcode":"20016",
    "sg:province":"MD",
    "sg:tags":[
        "publisher"
    ],
    "wof:name":"Fulcrum Publishihg",
    "wof:placetype":"venue"
},
  "geometry": {"coordinates":[-77.087301,38.935627],"type":"Point"}
}