{
  "type": "Feature",
  "properties": {
    "addr:full":"5107 13th St NW Washington MD 20011",
    "addr:housenumber":"5107",
    "addr:postcode":"20011",
    "addr:street":"13Th St Nw",
    "iso:country":"US",
    "sg:address":"5107 13th St NW",
    "sg:city":"Washington",
    "sg:classifiers":[
        {
            "category":"Manufacturing",
            "subcategory":"Printing",
            "type":"Manufacturing & Wholesale Goods"
        }
    ],
    "sg:phone":"+1 202 541 9700",
    "sg:postcode":"20011",
    "sg:province":"MD",
    "sg:tags":[
        "publisher"
    ],
    "sg:website":"www.gogardner.com",
    "wof:name":"GGC Publishing Inc",
    "wof:placetype":"venue"
},
  "geometry": {"coordinates":[-77.029622,38.952841],"type":"Point"}
}