{
  "type": "Feature",
  "properties": {
    "iso:country":"US",
    "sg:address":"4400 Jenifer St NW",
    "sg:city":"Washington",
    "sg:classifiers":[
        {
            "category":"Real Estate",
            "subcategory":"Real Estate Agent",
            "type":"Services"
        }
    ],
    "sg:phone":"+1 202 362 3600",
    "sg:postcode":"20015",
    "sg:province":"MD",
    "wof:name":"Thomas J Owen & Son Inc",
    "wof:placetype":"venue"
},
  "geometry": {"coordinates":[-77.08620000000001,38.95903],"type":"Point"}
}