{
  "type": "Feature",
  "properties": {
    "iso:country":"US",
    "sg:address":"6230 3rd St NW",
    "sg:city":"Washington",
    "sg:classifiers":[
        {
            "category":"Insurance",
            "subcategory":"Insurance Agent",
            "type":"Services"
        }
    ],
    "sg:phone":"+1 202 722 0377",
    "sg:postcode":"20011",
    "sg:province":"MD",
    "wof:name":"Minus & Assoc Insurance",
    "wof:placetype":"venue"
},
  "geometry": {"coordinates":[-77.016241,38.96577],"type":"Point"}
}