{
  "type": "Feature",
  "properties": {
    "addr:full":"4001 S Capitol St SW Washington MD 20032",
    "addr:housenumber":"4001",
    "addr:postcode":"20032",
    "addr:street":"S Capitol St Sw",
    "iso:country":"US",
    "sg:address":"4001 S Capitol St SW",
    "sg:city":"Washington",
    "sg:classifiers":[
        {
            "category":"Government",
            "subcategory":"Office",
            "type":"Public Place"
        }
    ],
    "sg:phone":"+1 202 645 4546",
    "sg:postcode":"20032",
    "sg:province":"MD",
    "sg:tags":[
        "village"
    ],
    "wof:name":"Washington Income Maintenance",
    "wof:placetype":"venue"
},
  "geometry": {"coordinates":[-77.00767399999999,38.830214],"type":"Point"}
}