{
  "type": "Feature",
  "properties": {
    "addr:full":"702 Jefferson St NW Washington MD 20011",
    "addr:housenumber":"702",
    "addr:postcode":"20011",
    "addr:street":"Jefferson St Nw",
    "iso:country":"US",
    "sg:address":"702 Jefferson St NW",
    "sg:city":"Washington",
    "sg:classifiers":[
        {
            "category":"Organizations",
            "subcategory":"Religious Organization",
            "type":"Services"
        }
    ],
    "sg:phone":"+1 202 726 4135",
    "sg:postcode":"20011",
    "sg:province":"MD",
    "sg:tags":[
        "clergy"
    ],
    "wof:name":"Bernard A Jefferson",
    "wof:placetype":"venue"
},
  "geometry": {"coordinates":[-77.023954,38.955182],"type":"Point"}
}