{
  "type": "Feature",
  "properties": {
    "iso:country":"US",
    "sg:address":"4000 Wisconsin Ave NW",
    "sg:city":"Washington",
    "sg:classifiers":[
        {
            "category":"Health Services",
            "subcategory":"Health Practitioner",
            "type":"Services"
        }
    ],
    "sg:phone":"+1 202 363 3665",
    "sg:postcode":"20016",
    "sg:province":"MD",
    "sg:tags":[
        "therapist",
        "physical"
    ],
    "wof:name":"Physiotherapy Associates Inc",
    "wof:placetype":"venue"
},
  "geometry": {"coordinates":[-77.076506,38.942215],"type":"Point"}
}