{
  "type": "Feature",
  "properties": {
    "addr:full":"3320 Brothers Pl SE Washington MD 20032",
    "addr:housenumber":"3320",
    "addr:postcode":"20032",
    "addr:street":"Brothers Pl Se",
    "iso:country":"US",
    "sg:address":"3320 Brothers Pl SE",
    "sg:city":"Washington",
    "sg:classifiers":[
        {
            "category":"Personal",
            "subcategory":"Barber",
            "type":"Services"
        }
    ],
    "sg:phone":"+1 202 561 0396",
    "sg:postcode":"20032",
    "sg:province":"MD",
    "wof:name":"My 3 Sons Unisex Shop",
    "wof:placetype":"venue"
},
  "geometry": {"coordinates":[-77.004189,38.842272],"type":"Point"}
}