{
  "type": "Feature",
  "properties": {
    "iso:country":"US",
    "sg:address":"7304 Georgia Ave NW",
    "sg:city":"Washington",
    "sg:classifiers":[
        {
            "category":"Banks & Credit Unions",
            "subcategory":"Investment Brokerage",
            "type":"Services"
        }
    ],
    "sg:phone":"+1 202 545 1220",
    "sg:postcode":"20012",
    "sg:province":"MD",
    "sg:tags":[
        "advisory",
        "financial"
    ],
    "wof:name":"First Contact Financial Svc",
    "wof:placetype":"venue"
},
  "geometry": {"coordinates":[-77.026533,38.979345],"type":"Point"}
}