{
  "type": "Feature",
  "properties": {
    "iso:country":"US",
    "sg:address":"5335 Wisconsin Ave NW",
    "sg:city":"Washington",
    "sg:classifiers":[
        {
            "category":"Organizations",
            "subcategory":"Non-profit Organization",
            "type":"Services"
        }
    ],
    "sg:phone":"+1 202 244 7900",
    "sg:postcode":"20015",
    "sg:province":"MD",
    "sg:website":"www.kidneywdc.org",
    "wof:name":"National Kidney Foundation",
    "wof:placetype":"venue"
},
  "geometry": {"coordinates":[-77.084846,38.959041],"type":"Point"}
}