{
  "type": "Feature",
  "properties": {
    "iso:country":"US",
    "sg:address":"501 Longfellow St NW",
    "sg:city":"Washington",
    "sg:classifiers":[
        {
            "category":"Professional",
            "subcategory":"Accounting & Tax Preparation",
            "type":"Services"
        }
    ],
    "sg:phone":"+1 202 882 7022",
    "sg:postcode":"20011",
    "sg:province":"MD",
    "sg:tags":[
        "billing"
    ],
    "wof:name":"PMBS Proctors Medical Bllng",
    "wof:placetype":"venue"
},
  "geometry": {"coordinates":[-77.022365,38.957446],"type":"Point"}
}