{
  "type": "Feature",
  "properties": {
    "addr:full":"1312 Floral St NW Washington MD 20012",
    "addr:housenumber":"1312",
    "addr:postcode":"20012",
    "addr:street":"Floral St Nw",
    "iso:country":"US",
    "sg:address":"1312 Floral St NW",
    "sg:city":"Washington",
    "sg:classifiers":[
        {
            "category":"Professional",
            "subcategory":"Management & Consulting",
            "type":"Services"
        }
    ],
    "sg:phone":"+1 202 829 7364",
    "sg:postcode":"20012",
    "sg:province":"MD",
    "sg:tags":[
        "consultant",
        "business"
    ],
    "wof:name":"Dennison Associates",
    "wof:placetype":"venue"
},
  "geometry": {"coordinates":[-77.031025,38.978613],"type":"Point"}
}