{
  "type": "Feature",
  "properties": {
    "addr:full":"6518 Westmoreland Ave Takoma Park MD 20912",
    "addr:housenumber":"6518",
    "addr:postcode":"20912",
    "addr:street":"Westmoreland Ave",
    "iso:country":"US",
    "sg:address":"6518 Westmoreland Ave",
    "sg:city":"Takoma Park",
    "sg:classifiers":[
        {
            "category":"Building & Trades",
            "subcategory":"Construction",
            "type":"Services"
        }
    ],
    "sg:phone":"+1 301 270 2817",
    "sg:postcode":"20912",
    "sg:province":"MD",
    "sg:tags":[
        "home",
        "improvement"
    ],
    "wof:name":"Henkai Home Improvement",
    "wof:placetype":"venue"
},
  "geometry": {"coordinates":[-77.006196,38.969904],"type":"Point"}
}