{
  "type": "Feature",
  "properties": {
    "iso:country":"US",
    "sg:address":"426 Rittenhouse St NW",
    "sg:city":"Washington",
    "sg:classifiers":[
        {
            "category":"Wholesale",
            "subcategory":"Toys & Hobbies",
            "type":"Manufacturing & Wholesale Goods"
        }
    ],
    "sg:phone":"+1 202 829 5900",
    "sg:postcode":"20011",
    "sg:province":"MD",
    "sg:tags":[
        "puppet",
        "marionette"
    ],
    "wof:name":"Silly Socks Puppet Theatre",
    "wof:placetype":"venue"
},
  "geometry": {"coordinates":[-77.01945,38.964876],"type":"Point"}
}