{
  "type": "Feature",
  "properties": {
    "iso:country":"US",
    "sg:address":"3301 New Mexico Ave NW",
    "sg:city":"Washington",
    "sg:classifiers":[
        {
            "category":"Health Services",
            "subcategory":"Optometrist",
            "type":"Services"
        }
    ],
    "sg:phone":"+1 202 363 5087",
    "sg:postcode":"20016",
    "sg:province":"MD",
    "wof:name":"Voorthuis Opticians Inc",
    "wof:placetype":"venue"
},
  "geometry": {"coordinates":[-77.086198,38.933985],"type":"Point"}
}