{
  "type": "Feature",
  "properties": {
    "iso:country":"US",
    "sg:address":"1600 Jonquil St NW",
    "sg:city":"Washington",
    "sg:classifiers":[
        {
            "category":"Education",
            "subcategory":"School",
            "type":"Public Place"
        }
    ],
    "sg:phone":"+1 202 723 5455",
    "sg:postcode":"20012",
    "sg:province":"MD",
    "wof:name":"Ostt-Olameinu",
    "wof:placetype":"venue"
},
  "geometry": {"coordinates":[-77.038422,38.983319],"type":"Point"}
}