{
  "type": "Feature",
  "properties": {
    "iso:country":"US",
    "sg:address":"6401 2nd Pl NW",
    "sg:city":"Washington",
    "sg:classifiers":[
        {
            "category":"Shopping",
            "subcategory":"Computers & Home Electronics",
            "type":"Retail Goods"
        }
    ],
    "sg:phone":"+1 202 726 3941",
    "sg:postcode":"20012",
    "sg:province":"MD",
    "sg:tags":[
        "high",
        "fidelity",
        "stereophonic"
    ],
    "sg:website":"www.dynamicsoundaudio.com",
    "wof:name":"Dynamic Sound",
    "wof:placetype":"venue"
},
  "geometry": {"coordinates":[-77.015072,38.968632],"type":"Point"}
}