{
  "type": "Feature",
  "properties": {
    "iso:country":"US",
    "sg:address":"5203 14th St NW",
    "sg:city":"Washington",
    "sg:classifiers":[
        {
            "category":"Professional",
            "subcategory":"Art Services",
            "type":"Services"
        }
    ],
    "sg:phone":"+1 202 726 4066",
    "sg:postcode":"20011",
    "sg:province":"MD",
    "sg:tags":[
        "photographer"
    ],
    "sg:website":"www.marvintjones.com",
    "wof:name":"Marvin T Jones & Assoc",
    "wof:placetype":"venue"
},
  "geometry": {"coordinates":[-77.033352,38.954061],"type":"Point"}
}