{
  "type": "Feature",
  "properties": {
    "iso:country":"US",
    "sg:address":"5481 31st St NW",
    "sg:city":"Washington",
    "sg:classifiers":[
        {
            "category":"Real Estate",
            "subcategory":"Developer",
            "type":"Services"
        }
    ],
    "sg:phone":"+1 202 966 3500",
    "sg:postcode":"20015",
    "sg:province":"MD",
    "wof:name":"ASL Development Corp",
    "wof:placetype":"venue"
},
  "geometry": {"coordinates":[-77.063024,38.963105],"type":"Point"}
}