{
  "type": "Feature",
  "properties": {
    "addr:full":"3311 10th Pl SE Washington MD 20032",
    "addr:housenumber":"3311",
    "addr:postcode":"20032",
    "addr:street":"10Th Pl Se",
    "iso:country":"US",
    "sg:address":"3311 10th Pl SE",
    "sg:city":"Washington",
    "sg:classifiers":[
        {
            "category":"Wholesale",
            "subcategory":"Home Furnishings",
            "type":"Manufacturing & Wholesale Goods"
        }
    ],
    "sg:phone":"+1 202 561 3001",
    "sg:postcode":"20032",
    "sg:province":"MD",
    "sg:tags":[
        "closet",
        "accessory"
    ],
    "wof:name":"Cathlin's Closet & Accessories",
    "wof:placetype":"venue"
},
  "geometry": {"coordinates":[-76.99199400000001,38.841267],"type":"Point"}
}