{
  "type": "Feature",
  "properties": {
    "iso:country":"US",
    "sg:address":"3609 Jenifer St NW",
    "sg:city":"Washington",
    "sg:classifiers":[
        {
            "category":"Professional",
            "subcategory":"Art Services",
            "type":"Services"
        }
    ],
    "sg:phone":"+1 202 364 1985",
    "sg:postcode":"20015",
    "sg:province":"MD",
    "sg:tags":[
        "photographer"
    ],
    "wof:name":"Fitz-Patrick Photography",
    "wof:placetype":"venue"
},
  "geometry": {"coordinates":[-77.06986,38.959101],"type":"Point"}
}