{
  "type": "Feature",
  "properties": {
    "addr:full":"7600 Georgia Ave NW Washington MD 20012",
    "addr:housenumber":"7600",
    "addr:postcode":"20012",
    "addr:street":"Georgia Ave Nw",
    "iso:country":"US",
    "sg:address":"7600 Georgia Ave NW",
    "sg:city":"Washington",
    "sg:classifiers":[
        {
            "category":"Professional",
            "subcategory":"Accounting & Tax Preparation",
            "type":"Services"
        }
    ],
    "sg:phone":"+1 202 291 8849",
    "sg:postcode":"20012",
    "sg:province":"MD",
    "sg:tags":[
        "accountant"
    ],
    "wof:name":"Joao F Campos & Assoc",
    "wof:placetype":"venue"
},
  "geometry": {"coordinates":[-77.026556,38.982724],"type":"Point"}
}