{
  "type": "Feature",
  "properties": {
    "iso:country":"US",
    "sg:address":"5523 Illinois Ave NW",
    "sg:city":"Washington",
    "sg:classifiers":[
        {
            "category":"Manufacturing",
            "subcategory":"Printing",
            "type":"Manufacturing & Wholesale Goods"
        }
    ],
    "sg:phone":"+1 202 723 0600",
    "sg:postcode":"20011",
    "sg:province":"MD",
    "sg:tags":[
        "lithographer"
    ],
    "wof:name":"Twin Image Lithograph",
    "wof:placetype":"venue"
},
  "geometry": {"coordinates":[-77.027728,38.956793],"type":"Point"}
}